{
  "id": "found-15-3d-shapes",
  "name": "हमारे आस-पास ठोस आकृतियाँ — लुढ़को, सरको और ढेर लगाओ",
  "grade": 1,
  "strand": "geometry",
  "prerequisites": [
    "found-10-shapes"
  ],
  "whatIsIt": "सपाट आकृतियाँ कागज़ पर रहती हैं, पर असली चीज़ें ठोस होती हैं — तुम उन्हें पकड़ सकते हो। गेंद एक गोला है (यह हर तरफ़ लुढ़कती है)। डिब्बा या पासा एक घन है (इसके 6 सपाट फलक होते हैं, और यह ढेर में रखा जाता है)। टिन का डिब्बा एक बेलन है (ऊपर-नीचे सपाट, बीच में गोल — यह लुढ़कता भी है और ढेर भी लगता है)। आइसक्रीम कोन एक शंकु है (गोल तल, एक नोक)। ठोस आकृतियों में फलक (सपाट सतहें), किनारे (जहाँ फलक मिलते हैं) और कोने (नोकें) होते हैं।",
  "whyNeeded": "बच्चा जो कुछ भी छूता है वह एक ठोस आकृति है — गेंदें, डिब्बे, टिन, पासे, पार्टी टोपियाँ। कौन-सी आकृतियाँ लुढ़कती हैं, सरकती हैं और ढेर लगती हैं, यह जानना ब्लॉक बनाने, पैक करने और सपाट चित्रों पर जाने से पहले दुनिया को समझने में मदद करता है।",
  "realLifeUses": [
    "गेंद लुढ़कती है क्योंकि वह एक गोला है",
    "डिब्बे साफ़-सुथरे ढेर लगते हैं क्योंकि वे घन हैं",
    "टिन का डिब्बा करवट पर लुढ़कता है पर अपने सिरों पर ढेर लगता है",
    "आइसक्रीम कोन और पार्टी टोपी शंकु हैं"
  ],
  "vocabulary": [
    {
      "term": "गोला",
      "meaning": "गेंद जैसा बिलकुल गोल ठोस — यह लुढ़कता है और इसका कोई कोना नहीं होता।"
    },
    {
      "term": "घन",
      "meaning": "पासे जैसी डिब्बा-आकृति जिसके 6 बराबर सपाट वर्गाकार फलक होते हैं।"
    },
    {
      "term": "बेलन",
      "meaning": "टिन जैसी आकृति — दो सपाट गोल सिरे और एक घुमावदार सतह।"
    },
    {
      "term": "फलक / किनारा / कोना",
      "meaning": "फलक एक सपाट सतह है; किनारा वह जगह है जहाँ दो फलक मिलते हैं; कोना एक नोक है।"
    }
  ],
  "story": {
    "title": "अनु की खिलौना टोकरी",
    "characters": [
      "अनु",
      "दादी"
    ],
    "text": "अनु अपनी खिलौना टोकरी उलट देती है: एक गेंद, एक पासा, और बिस्कुट का एक टिन। 'कौन-कौन लुढ़कते हैं?' दादी पूछती हैं। अनु उन्हें धकेलती है: गेंद लुढ़क जाती है, टिन करवट पर लुढ़कता है, पर पासा बस सरककर रुक जाता है। 'पासे के सपाट फलक हैं — मैं इन्हें गिन सकती हूँ!' वह हर तरफ़ छूती है: 1, 2, 3, 4, 5, 6। 'छह फलक!' दादी ताली बजाती हैं। 'यह एक घन है।'",
    "extractedProblem": "एक पासे (घन) के कितने सपाट फलक होते हैं?",
    "answerInStory": "6 — अनु घन पर छह सपाट वर्गाकार फलक गिनती है।"
  },
  "visual": {
    "component": "Solid3D",
    "props": {
      "solids": [
        {
          "kind": "sphere",
          "label": "गेंद (गोला)"
        },
        {
          "kind": "cube",
          "label": "डिब्बा (घन)"
        },
        {
          "kind": "cylinder",
          "label": "टिन (बेलन)"
        },
        {
          "kind": "cone",
          "label": "शंकु"
        }
      ]
    },
    "caption": "असली 3D ठोस जिन्हें तुम घुमा सकते हो: गोला लुढ़कता है, घन ढेर लगता है (6 फलक), बेलन दोनों करता है, शंकु की एक नोक होती है।"
  },
  "teachingGallery": [
    {
      "title": "इसे लुढ़काओ या ढेर लगाओ?",
      "note": "गोल हिस्से लुढ़कते हैं; सपाट फलक किसी आकृति को ढेर और सरकने देते हैं।",
      "examples": [
        {
          "component": "GeometryCanvas",
          "props": {
            "shapes": [
              {
                "kind": "circle",
                "label": "गोला → लुढ़कता है"
              }
            ]
          },
          "caption": "गेंद (गोला) का कोई सपाट फलक नहीं, इसलिए यह कहीं भी लुढ़कती है।"
        },
        {
          "component": "GeometryCanvas",
          "props": {
            "shapes": [
              {
                "kind": "square",
                "w": 3,
                "h": 3,
                "label": "घन → 6 फलक"
              }
            ]
          },
          "caption": "पासे (घन) के 6 सपाट फलक, 8 कोने और 12 किनारे होते हैं — यह ढेर लगता है।"
        },
        {
          "component": "GeometryCanvas",
          "props": {
            "shapes": [
              {
                "kind": "rect",
                "w": 3,
                "h": 4,
                "label": "टिन → बेलन"
              }
            ]
          },
          "caption": "टिन का डिब्बा (बेलन) करवट पर लुढ़कता है पर अपने सपाट सिरों पर ढेर लगता है।"
        }
      ]
    }
  ],
  "standardMethod": {
    "summary": "ठोस को उठाओ। सपाट फलकों और गोल हिस्सों को महसूस करो। गोल हिस्से लुढ़कते हैं; सपाट फलक ढेर और सरकते हैं। हर एक को छूकर फलक, कोने और किनारे गिनो।",
    "steps": [
      "वस्तु को पकड़ो और सपाट फलक तथा गोल हिस्से ढूँढो।",
      "अगर यह पूरी गोल है (गेंद), तो यह गोला है और लुढ़कती है।",
      "अगर इसके सपाट वर्गाकार फलक हैं (पासा), तो यह घन है — 6 फलक गिनो।",
      "टिन (बेलन) के गोल सिरे होते हैं और करवट पर लुढ़कता है; शंकु की एक नोक होती है।",
      "इसे परखो: क्या यह लुढ़कता है, सरकता है, या ढेर लगता है?"
    ]
  },
  "workedExamples": [
    {
      "problem": "एक घन (पासे) के कितने सपाट फलक होते हैं?",
      "steps": [
        "हर सपाट तरफ़ को छूकर गिनो।",
        "ऊपर, नीचे, और चारों ओर के चार = 1,2,3,4,5,6।",
        "एक घन के 6 फलक होते हैं।"
      ],
      "answer": "6"
    },
    {
      "problem": "क्या गेंद (गोला) लुढ़कती है या ढेर लगती है?",
      "steps": [
        "गेंद हर तरफ़ गोल है, कोई सपाट फलक नहीं।",
        "बिना सपाट फलक के यह ढेर के लिए स्थिर नहीं रह सकती।",
        "तो गेंद लुढ़कती है।"
      ],
      "answer": "यह लुढ़कती है"
    }
  ],
  "commonMistakes": [
    {
      "mistakeTag": "flat-vs-solid",
      "mistake": "गेंद को 'वृत्त' या पासे को 'वर्ग' कहना — सपाट आकृतियों को ठोस से मिला देना।",
      "fix": "वृत्त सपाट है (कागज़ पर); गेंद एक ठोस है जिसे तुम पकड़ सकते हो (गोला)। वर्ग सपाट है; पासा एक घन है।"
    },
    {
      "mistakeTag": "faces-miscount",
      "mistake": "यह कहना कि घन के 4 फलक होते हैं (ऊपर और नीचे भूल जाना)।",
      "fix": "सभी तरफ़ गिनो: चारों ओर के 4 और ऊपर तथा नीचे = 6 फलक।"
    }
  ],
  "practice": {
    "easy": [
      {
        "id": "f15-e1",
        "type": "number",
        "q": "एक घन (पासे) के कितने सपाट फलक होते हैं?",
        "answer": "6",
        "hintLadder": [
          "हर सपाट तरफ़ गिनो।",
          "चारों ओर के 4, और ऊपर-नीचे।",
          "6।"
        ]
      },
      {
        "id": "f15-e2",
        "type": "mcq",
        "q": "कौन लुढ़कता है?",
        "options": [
          {
            "label": "गेंद (गोला)"
          },
          {
            "label": "डिब्बा (घन)",
            "mistakeTag": "flat-vs-solid"
          }
        ],
        "answer": "गेंद (गोला)",
        "hintLadder": [
          "गोल चीज़ें लुढ़कती हैं।",
          "डिब्बे के सपाट फलक होते हैं।",
          "गेंद लुढ़कती है।"
        ]
      }
    ],
    "medium": [
      {
        "id": "f15-m1",
        "type": "number",
        "q": "एक घन के कितने कोने (नोकें) होते हैं?",
        "answer": "8",
        "hintLadder": [
          "पासे की नुकीली कोनों को गिनो।",
          "ऊपर 4, नीचे 4।",
          "8।"
        ]
      },
      {
        "id": "f15-m2",
        "type": "mcq",
        "q": "टिन का डिब्बा एक…",
        "options": [
          {
            "label": "बेलन — करवट पर लुढ़कता है, सिरों पर ढेर लगता है"
          },
          {
            "label": "6 फलकों वाला घन",
            "mistakeTag": "faces-miscount"
          }
        ],
        "answer": "बेलन — करवट पर लुढ़कता है, सिरों पर ढेर लगता है",
        "hintLadder": [
          "इसके गोल सिरे होते हैं।",
          "गोल सिरे + घुमावदार सतह।",
          "एक बेलन।"
        ]
      }
    ],
    "challenge": [
      {
        "id": "f15-c1",
        "type": "number",
        "q": "एक घन के कितने किनारे (जहाँ दो फलक मिलते हैं) होते हैं?",
        "answer": "12",
        "hintLadder": [
          "पासे की रेखाओं को गिनो।",
          "ऊपर 4, नीचे 4, खड़ी 4।",
          "12।"
        ]
      },
      {
        "id": "f15-c2",
        "type": "mcq",
        "q": "रिया गेंद को 'वृत्त' कहती है। सही सुधार क्या है?",
        "options": [
          {
            "label": "गेंद एक ठोस गोला है; वृत्त कागज़ पर सपाट होता है"
          },
          {
            "label": "गेंद और वृत्त एक ही हैं",
            "mistakeTag": "flat-vs-solid"
          }
        ],
        "answer": "गेंद एक ठोस गोला है; वृत्त कागज़ पर सपाट होता है",
        "hintLadder": [
          "क्या तुम वृत्त पकड़ सकते हो?",
          "वृत्त सपाट है; गेंद ठोस है।",
          "गेंद एक गोला है।"
        ]
      }
    ]
  },
  "masteryCheck": {
    "questions": [
      {
        "id": "f15-x1",
        "type": "number",
        "q": "एक घन पर सपाट फलक?",
        "answer": "6",
        "hintLadder": [
          "हर तरफ़ गिनो।",
          "4 + ऊपर + नीचे।",
          "6।"
        ]
      },
      {
        "id": "f15-x2",
        "type": "mcq",
        "q": "कौन-सी आकृति सबसे अच्छे ढेर लगती है?",
        "options": [
          {
            "label": "डिब्बा (घन) — इसके सपाट फलक होते हैं"
          },
          {
            "label": "गेंद (गोला)",
            "mistakeTag": "flat-vs-solid"
          }
        ],
        "answer": "डिब्बा (घन) — इसके सपाट फलक होते हैं",
        "hintLadder": [
          "सपाट फलक ढेर लगते हैं।",
          "गेंद लुढ़क जाती है।",
          "डिब्बा ढेर लगता है।"
        ]
      },
      {
        "id": "f15-x3",
        "type": "number",
        "q": "एक घन पर कोने?",
        "answer": "8",
        "hintLadder": [
          "पासे की नोकें।",
          "ऊपर 4, नीचे 4।",
          "8।"
        ]
      },
      {
        "id": "f15-x4",
        "type": "mcq",
        "q": "एक आइसक्रीम कोन एक…",
        "options": [
          {
            "label": "शंकु — गोल तल और एक नोक"
          },
          {
            "label": "गेंद जैसा गोला",
            "mistakeTag": "flat-vs-solid"
          }
        ],
        "answer": "शंकु — गोल तल और एक नोक",
        "hintLadder": [
          "यह एक नोक पर आता है।",
          "गोल तल, एक नोक।",
          "एक शंकु।"
        ]
      }
    ],
    "passThreshold": 0.75,
    "requireTeachBack": true
  },
  "teachBackPrompt": "घर पर एक गेंद, एक डिब्बा और एक टिन ढूँढो। किसी बड़े को दिखाओ कि कौन लुढ़कता है, कौन ढेर लगता है, और कौन दोनों करता है। डिब्बे के 6 फलक ज़ोर से गिनो, और हर ठोस का नाम लो: गोला, घन, बेलन।",
  "revisionCard": {
    "summary": "ठोस वे आकृतियाँ हैं जिन्हें तुम पकड़ सकते हो। गोला (गेंद) लुढ़कता है, कोई कोना नहीं। घन (पासा/डिब्बा) के 6 सपाट फलक, 8 कोने, 12 किनारे — यह ढेर लगता है। बेलन (टिन) करवट पर लुढ़कता है, सिरों पर ढेर लगता है। शंकु का गोल तल और एक नोक होती है। सपाट आकृतियाँ कागज़ पर रहती हैं; ठोस तुम्हारे हाथों में।",
    "reviewAfterDays": [
      3,
      7,
      21
    ]
  },
  "meta": {
    "version": "1.0.0",
    "curriculum": "CBSE/NCERT NEP Foundational — Class 1-2 (solid shapes)",
    "language": "hi",
    "authoredBy": "FearlessMath authoring team",
    "reviewStatus": "draft",
    "reviewedBy": ""
  },
  "rememberIt": {
    "hook": "ठोस आकृतियाँ जिन्हें तुम पकड़ सकते हो: घन, गोला, बेलन, शंकु",
    "unpack": "गेंद = गोला (लुढ़कता है), डिब्बा = घनाभ, टिन = बेलन, पार्टी टोपी = शंकु। सपाट फलक बनाम घुमावदार पर ध्यान दो।"
  },
  "studentQuestions": [
    {
      "q": "घन और गोले में फ़र्क कैसे बताऊँ?",
      "a": "घन के सपाट वर्गाकार फलक और कोने होते हैं; गोला हर तरफ़ गोल होता है और लुढ़कता है।"
    },
    {
      "q": "कौन-सी 3D आकृतियाँ लुढ़कती हैं?",
      "a": "गोला, बेलन और शंकु - इनकी घुमावदार सतहें होती हैं। घन नहीं लुढ़केगा।"
    }
  ]
}
